sanic_sockjs/__init__.py
sanic_sockjs/exceptions.py
sanic_sockjs/protocol.py
sanic_sockjs/route.py
sanic_sockjs/session.py
sanic_sockjs/transports/__init__.py
sanic_sockjs/transports/base.py
sanic_sockjs/transports/eventsource.py
sanic_sockjs/transports/htmlfile.py
sanic_sockjs/transports/jsonp.py
sanic_sockjs/transports/rawwebsocket.py
sanic_sockjs/transports/utils.py
sanic_sockjs/transports/websocket.py
sanic_sockjs/transports/xhr.py
sanic_sockjs/transports/xhrsend.py
sanic_sockjs/transports/xhrstreaming.py
sanic_sockjs-0.1.0.dist-info/LICENSE.txt
sanic_sockjs-0.1.0.dist-info/METADATA
sanic_sockjs-0.1.0.dist-info/WHEEL
sanic_sockjs-0.1.0.dist-info/top_level.txt
sanic_sockjs-0.1.0.dist-info/RECORD
