Metadata-Version: 2.1
Name: sanic-sockjs
Version: 0.1.0
Summary: SockJS server implementation for Sanic.
Home-page: https://github.com/ashleysommer/sanic-sockjs/
Author: Ashley Sommer
Author-email: ashleysommer@gmail.com
License: Apache 2
Platform: UNKNOWN
Classifier: License :: OSI Approved :: Apache Software License
Classifier: Intended Audience :: Developers
Classifier: Programming Language :: Python
Classifier: Programming Language :: Python :: 3
Classifier: Programming Language :: Python :: 3.6
Classifier: Programming Language :: Python :: 3.7
Classifier: Programming Language :: Python :: Implementation :: CPython
Classifier: Topic :: Internet :: WWW/HTTP
Classifier: Framework :: AsyncIO
Requires-Python: >=3.6.0
Requires-Dist: yarl (==1.4.2)
Requires-Dist: multidict (<5.0,>=4.0)
Requires-Dist: websockets (<9.0,>=6.0)
Requires-Dist: sanic (>=19.3.1)
